README.md
setup.py
qwert1234/__init__.py
qwert1234/back.py
qwert1234/setup.py
qwert1234.egg-info/PKG-INFO
qwert1234.egg-info/SOURCES.txt
qwert1234.egg-info/dependency_links.txt
qwert1234.egg-info/top_level.txt